psscraper/PowerschoolBrowser.py
psscraper/__init__.py
psscraper/scrapper/PowerschoolAssignmentScrapper.py
psscraper/scrapper/PowerschoolClassInfoScrapper.py
psscraper/scrapper/PowerschoolScrapper.py
psscraper/scrapper/__init__.py
psscraper-2.0.0.dist-info/LICENSE
psscraper-2.0.0.dist-info/METADATA
psscraper-2.0.0.dist-info/WHEEL
psscraper-2.0.0.dist-info/top_level.txt
psscraper-2.0.0.dist-info/RECORD
