Metadata-Version: 2.1
Name: psscraper
Version: 2.0.0
Summary: A web scrapper library for powerschool websites.
Home-page: https://github.com/Desperationis/psscraper
Author: Diego Contreras
Author-email: smarttdiego@gmail.com
License: UNKNOWN
Project-URL: Bug Tracker, https://github.com/Desperationis/psscraper/issues
Platform: UNKNOWN
Classifier: Programming Language :: Python :: 3
Classifier: License :: OSI Approved :: GNU General Public License v3 (GPLv3)
Classifier: Operating System :: OS Independent
Requires-Python: >=3.6
License-File: LICENSE
